server.py
test_auth.py
dataforseo_mcp_server-1.0.0.dist-info/licenses/LICENSE
dataforseo_mcp_server-1.0.0.dist-info/METADATA
dataforseo_mcp_server-1.0.0.dist-info/WHEEL
dataforseo_mcp_server-1.0.0.dist-info/top_level.txt
dataforseo_mcp_server-1.0.0.dist-info/RECORD
