Metadata-Version: 2.4
Name: dataforseo-mcp-server
Version: 1.0.0
Summary: MCP server for tracking brand visibility in LLMs (ChatGPT, Claude, Gemini, Perplexity) using DataForSEO API
Author-email: Chetan Parma <chetanparma1@gmail.com>
License: MIT
Project-URL: Homepage, https://github.com/chetanparma1/dataforseo-ai-mcp-server
Project-URL: Documentation, https://github.com/chetanparma1/dataforseo-ai-mcp-server#readme
Project-URL: Repository, https://github.com/chetanparma1/dataforseo-ai-mcp-server
Project-URL: Issues, https://github.com/chetanparma1/dataforseo-ai-mcp-server/issues
Keywords: mcp,mcp-server,claude,chatgpt,llm,seo,dataforseo,brand-tracking,ai-optimization
Classifier: Development Status :: 4 - Beta
Classifier: Intended Audience :: Developers
Classifier: License :: OSI Approved :: MIT License
Classifier: Programming Language :: Python :: 3
Classifier: Programming Language :: Python :: 3.11
Classifier: Programming Language :: Python :: 3.12
Classifier: Programming Language :: Python :: 3.13
Classifier: Topic :: Software Development :: Libraries :: Python Modules
Classifier: Topic :: Internet :: WWW/HTTP :: Indexing/Search
Requires-Python: >=3.11
License-File: LICENSE
Requires-Dist: fastmcp>=0.1.0
Requires-Dist: httpx>=0.24.0
Requires-Dist: pydantic>=2.0.0
Requires-Dist: python-dotenv>=1.0.0
Dynamic: license-file
